rust_dfs-0.3.0.dist-info/METADATA
rust_dfs-0.3.0.dist-info/WHEEL
rust_dfs/rust_dfs.pyi
rust_dfs/generate_fake_dataframe.py
rust_dfs/tests/test_one.py
rust_dfs/__init__.py
rust_dfs/utils.py
rust_dfs/polars_primitives.py
rust_dfs/benchmarks/benchmark1.py
rust_dfs/py.typed
rust_dfs/rust_dfs.cpython-310-darwin.so
rust_dfs-0.3.0.dist-info/RECORD
