Metadata-Version: 2.1
Name: rust_dfs
Version: 0.3.0
Classifier: Programming Language :: Rust
Classifier: Programming Language :: Python :: Implementation :: CPython
Classifier: Programming Language :: Python :: Implementation :: PyPy
Requires-Dist: featuretools>=1.11.1
Requires-Dist: pytest==7.1.2
Requires-Python: >=3.7
